Workbook

Sheet About
A1: AR Open Items - Power Query cleaning example
A3: A messy accounts-receivable open-items print (670 lines, 497 real open items) cleaned with Power Query.
A4: All customers, invoice numbers and amounts are fictitious.
A6: Sheets
A7: Raw_Data The export exactly as it came out: titles, page footers, subtotals, repeated headers, duplicates, mixed formats.
A8: Cleaned_Data The output of the AR_Open_Items_Clean query (one row per open document, typed columns, ageing added).
A9: Before_After 30 real fields from the raw file next to what the query turns them into, and which step does it.
A10: Issues_Log Every problem found in the raw file, how it is handled, and how many lines it touched.
A11: Aging_Summary Ageing by bucket and currency, and by customer. Live formulas on Cleaned_Data. Reconciled to the report footer.
A12: Cust_Master / Rep_Alias The two lookup tables the query joins to.
A13: M_Code The main query, for pasting into Data > Get Data > Blank Query > Advanced Editor.
A15: Running it yourself
... A21: Credit notes and on-account receipts are always negative. Blank currency is taken as INR. Blank terms use the customer master default.

Sheet Raw_Data
A1: Hosur Road Industrial Supplies Pvt Ltd
A2: Accounts Receivable - Open Items by Customer
A3: As on 30/09/2026 | J3: Run date: 01/10/2026 08:42
A4: Selection: all customers, all posting keys | Currency: document currency
A6: Cust Code | B6: Customer Name | C6: Doc No | D6: Type | E6: Doc Date | F6: Due Date | G6: Amount | H6: Curr | I6: Terms | J6: Sales Rep | K6: PO / Ref | L6: Remarks
A7: C10008 | B7: Sagar Polypack | C7: HR/25-26/01088 | D7: INV | E7: 09/12/2025 | F7: 08/01/2026 | G7: 96,594.74 | H7: INR | I7: Net 30 | J7: Anitha Rao | K7: PO/26/738
C8: JV/25-26/0031 | D8: JV | E8: 27-Feb-26 | G8: -18,185.08 | H8: INR | J8: A. Rao
C9: HR/25-26/03028 | D9: INV | E9: 03/03/2026 | F9: 02/04/2026 | G9: 44,604.00 | H9: inr | J9: Anitha R. | K9: none | L9: PTP 15/10
C10: HR/25-26/04023 | D10: INV | E10: 29/03/2026 | G10: 39,270.00 | H10: ₹ | I10: Net 30 | J10: Anitha Rao | K10: PO/26/116
C11: HR/26-27/00424 | D11: INV | E11: 05/06/2026 | F11: 05/07/2026 | G11: 104,685.00 | H11: INR | I11: 30 days | J11: anitha rao | K11: PO-5305
C12: HR/26-27/00716 | D12: INV | E12: 11-Jul-26 | F12: 10-Aug-26 | G12: Rs. 224,663.47 | H12: INR | I12: 30 Days | J12: Anitha R. | K12: PO/26/505
C13: HR/26-27/00691 | D13: INV | E13: 08/07/2026 | F13: 07/08/2026 | G13: 17346.00 | H13: INR | I13: Net 30
C14: DN/26-27/0016 | D14: DN | E14: 02/08/2026 | F14: 01/09/2026 | G14: 1,988.36 | H14: inr | I14: Net 30 | J14: Anitha R. | K14: PO-5807
C15: HR/26-27/01104 | D15: INV | E15: 02-Aug-26 | F15: 01-Sep-26 | G15: 80,478.64 | I15: Net 30 | J15: ANITHA R | K15: WO-624
C16: HR/26-27/01160 | D16: INV | E16: 06/08/2026 | F16: 05/09/2026 | G16: 138,916.85 | H16: INR | I16: NET30 | J16: ANITHA R | K16: PO-6241
C17: HR/26-27/01487 | D17: INV | E17: 46260 | F17: 46275 | G17: 50,268.00 | H17: INR | I17: Net 15 | J17: Anitha Rao | K17: 4597152166
C18: HR/26-27/01874 | D18: INV | E18: 09/09/2026 | F18: 09/10/2026 | G18: Rs. 84,684.97 | H18: INR | I18: 30 days | J18: anitha rao
C19: HR/26-27/02095 | D19: INV | E19: 17/09/2026 | F19: 17/10/2026 | G19: 368450.74 | H19: INR | I19: 30 days | J19: A. Rao | K19: PO/25/481
C20: HR/26-27/02244 | D20: INV | E20: 21/09/2026 | F20: 21/10/2026 | G20: 192,340.00 | H20: INR | I20: Net 30 | J20: Anitha R. | K20: PO-8122
C21: HR/26-27/02376 | D21: INV | E21: 26 Sep 2026 | F21: 26/10/2026 | G21: 147,618.00 | H21: INR | I21: Net30 | J21: Anitha Rao | K21: PO/26/467
C22: ** Customer total ** | G22: 15,73,723.69 | H22: INR
A23: C10011 | B23: Sri Lakshmi Traders | C23: CN/26-27/0071 | D23: CR NOTE | E23: 08/08/2026 | G23: 20,619.99- | H23: INR | J23: Divya N.
C24: HR/26-27/01548 | D24: INV | E24: 27/08/2026 | F24: 26/09/2026 | G24: 140,774.00 | H24: INR | I24: Net30 | J24: Divya Nair | K24: -
C25: ** Customer total ** | G25: 1,20,154.01 | H25: INR
A27: C10017 | B27: Jayanagar Hardware Mart | C27: HR/26-27/00720 | D27: INV | E27: 14/07/2026 | F27: 29/07/2026 | G27: Rs. 61,360.00 | H27: INR | I27: Net15 | J27: A. Rao | K27: NA
C28: HR/26-27/01368 | D28: INV | E28: 2026-08-21 | F28: 05/09/2026 | G28: 28,084.00 | H28: INR | I28: Net15 | J28: Anitha Rao
C29: HR/26-27/01665 | D29: INV | E29: 02/09/2026 | F29: 17/09/2026 | G29: 15,340 | H29: INR | I29: Net 15 | J29: anitha rao
C30: ** Customer total ** | G30: 1,04,784.00 | H30: INR
A32: C10021 | B32: Konkan Marine Equipments | C32: HR/25-26/00693 | D32: INV | E32: 13/11/2025 | F32: 28/12/2025 | G32: 57,015.00 | H32: INR | I32: Net 45 | J32: Suresh Babu | K32: PO-2314 | L32: part payment recd, bal pending
C33: HR/25-26/02229 | D33: INV | E33: 17/01/2026 | F33: 03/03/2026 | G33: 560,146.00 | H33: inr | I33: 45 Days | J33: anitha rao | K33: PO/25/476
C34: HR/25-26/03868 | D34: inv | E34: 26/03/2026 | F34: 10/05/2026 | G34: Rs. 27,258.00 | H34: INR | I34: NET45 | J34: anitha rao | K34: PO/25/676
C35: HR/25-26/04223 | D35: INV | E35: 31/03/2026 | F35: 15/05/2026 | G35: 25,760.00 | H35: INR | I35: NET45 | J35: Anitha Rao
C36: DN/26-27/0002 | D36: Dr Note | E36: 05/06/2026 | F36: 20/07/2026 | G36: 4,480.00 | H36: INR | I36: Net 45 | J36: Anitha Rao | K36: WO-495
C37: HR/26-27/00489 | D37: INV | E37: 18/06/2026 | F37: 02-Aug-26 | G37: 402,380.00 | H37: INR | I37: 45 Days | J37: Anitha Rao
C38: HR/26-27/00413 | D38: INV | E38: 03-Jun-26 | F38: 18-Jul-26 | G38: 606,900.00 | H38: INR | I38: 45 Days | J38: Ramesh | K38: PO-1164
C39: HR/26-27/00876 | D39: INV | E39: 21-Jul-26 | F39: 04-Sep-26 | G39: 46,451.21 | H39: INR | I39: Net 45 | J39: A. Rao | K39: PO-6449
C40: HR/26-27/00973 | D40: INV | E40: 26/07/2026 | F40: 09/09/2026 | G40: 11,303.68 | H40: INR | I40: NET45 | K40: 4512095782
C41: HR/26-27/01162 | D41: INV | E41: 07.08.2026 | F41: 21.09.2026 | G41: 56,286.00 | H41: INR | I41: Net 45 | J41: Anitha Rao | K41: PO-4393
C42: HR/26-27/01344 | D42: INV | E42: 19/08/2026 | F42: 03/10/2026 | G42: 66,394.53 | H42: INR | I42: N45 | J42: anitha rao | K42: WO-551
C43: HR/ 26-27/01363 | D43: INV | E43: 21-Aug-26 | F43: 20-Oct-26 | G43: 35,754.00 | H43: INR | I43: Net 60 | J43: Anitha Rao | K43: PO-9573
C44: CN/26-27/0087 | D44: Cr Note | E44: 22/08/2026 | F44: 22/08/2026 | G44: 55,658.43- | H44: INR | I44: Immediate | K44: ret. goods
C45: HR/26-27/01968 | D45: INV | E45: 14/09/2026 | F45: 29/10/2026 | G45: 45062.24 | H45: INR | I45: Net 45 | J45: Anitha R. | K45: PO/25/366
C46: HR/26-27/01988 | D46: INV | E46: 15/09/2026 | F46: 30/10/2026 | G46: 73,925.76 | H46: Rs | I46: 45 Days | J46: Anitha Rao | K46: WO-367
C47: hr/26-27/02020 | D47: INV | E47: 15/09/2026 | G47: 81920.00 | H47: INR | I47: NET45 | J47: Anitha R. | K47: PO/26/267
C48: HR/26-27/02104 | D48: INV | E48: 18/09/2026 | F48: 02/11/2026 | G48: 4,76,838.00 | H48: INR | I48: 45 days | J48: anitha rao | K48: PO-9754
C49: HR/26-27/02194 | D49: INV | E49: 20/09/2026 | F49: 04/11/2026 | G49: 37,760.00 | H49: INR | I49: 45 days | J49: A. Rao | K49: PO-8511
C50: ** Customer total ** | G50: 25,59,975.99 | H50: INR
A52: C10029 | B52: Peenya Precision Tools | C52: HR/26-27/00299 | D52: INV | E52: 21/05/2026 | F52: 05/07/2026 | G52: 46,964.00 | H52: INR | I52: NET45 | J52: S Babu | K52: PO-9393 | L52: PTP 15/10
A53: Page 1 of 13
A55: Hosur Road Industrial Supplies Pvt Ltd | G55: AR Open Items
A56: Cust Code | B56: Customer Name | C56: Doc No | D56: Type | E56: Doc Date | F56: Due Date | G56: Amount | H56: Curr | I56: Terms | J56: Sales Rep | K56: PO / Ref | L56: Remarks
A57: C10029 | B57: Peenya Precision Tools | C57: HR/26-27/00299 | D57: INV | E57: 21/05/2026 | F57: 05/07/2026 | G57: 46,964.00 | H57: INR | I57: NET45 | J57: S Babu | K57: PO-9393 | L57: PTP 15/10
C58: HR/26-27/00481 | D58: INV | E58: 17/06/2026 | F58: 17/07/2026 | G58: 38,114.00 | H58: Rs | I58: Net 30 | K58: WO-204
C59: HR/26-27/00546 | D59: INV | E59: 25/06/2026 | F59: 10/07/2026 | G59: 33,866.00 | H59: INR | I59: Net 15 | J59: Suresh Babu | K59: PO-9408 | L59: dispute qty
C60: HR/26-27/00855 | D60: Inv | E60: 21/07/2026 | F60: 20/08/2026 | G60: 52,392.00 | H60: INR | I60: Net30 | J60: suresh | K60: WO-876 | L60: dispute qty
C61: HR/26-27/01674 | D61: INVOICE | E61: 02/09/2026 | F61: 17/10/2026 | G61: 148102.33 | H61: INR | I61: Net 45 | J61: suresh | K61: PO-1581
C62: HR/26-27/02100 | D62: INV | E62: 17/09/2026 | F62: 01/11/2026 | G62: 49560.00 | I62: 45 Days | J62: Suresh Babu | K62: PO-3043
C63: HR/26-27/01660 | D63: INV | E63: 02/09/2026 | F63: 17/10/2026 | G63: 48,852.00 | H63: INR | I63: Net 45 | J63: Suresh B. | K63: WO-141
C64: HR/26-27/02169 | D64: INV | E64: 19/09/2026 | F64: 03/11/2026 | G64: 125,272.26 | H64: INR | I64: Net 45 | J64: Suresh Babu | K64: WO-798
C65: HR/26-27/02389 | D65: INV | E65: 27/09/2026 | F65: 27/10/2026 | G65: 179,664.78 | H65: INR | I65: 30 days | J65: SURESH B | K65: PO-5221
C66: HR/26-27/02355 | D66: INV | E66: 25/09/2026 | F66: 09/11/2026 | G66: 65,735.53 | H66: INR | I66: 45 Days | J66: SURESH B | K66: as discussed
C67: ** Customer total ** | G67: 7,88,522.90 | H67: INR
A69: c10031 | B69: Hosakote Industrial Estate Traders | C69: HR/25-26/02270 | D69: INV | E69: 19/01/2026 | F69: 18/02/2026 | G69: Rs. 87,438.00 | H69: inr | I69: 30 days | J69: Divya Nair | K69: PO-2191
C70: HR/25-26/02496 | D70: INV | E70: 09/02/2026 | F70: 11/03/2026 | G70: 6,844.00 | H70: INR | I70: N30 | J70: divya | K70: PO-4685
C71: HR/26-27/00371 | D71: INV | E71: 27/05/2026 | F71: 26/06/2026 | G71: 89,798.00 | H71: INR | I71: Net 30 | J71: Divya Nair | K71: PO-5478
C72: RCT/26-27/00024 | D72: RCT | E72: 11-Jun-26 | G72: 4,52,900.00 | H72: INR | I72: Immediate | J72: DIVYA N
C73: HR/26-27/00901 | D73: INV | E73: 2026-07-23 | G73: 12,238.72 | H73: INR | I73: 30D | J73: Divya Nair | K73: PO-6587
C74: HR/26-27/01897 | D74: INV | E74: 10-Sep-26 | F74: 10-Oct-26 | G74: 35,282.00 | H74: inr | I74: Net30 | J74: divya | K74: WO-380
C75: CN/26-27/0055 | D75: CN | E75: 25-Jul-26 | F75: 25-Jul-26 | G75: -15,900.00 | H75: INR | J75: Divya Nair
C76: HR/26-27/01962 | D76: INV | E76: 13/09/2026 | G76: 146,320.00 | H76: INR | I76: 30D | J76: Suresh Babu | K76: PO-4331
C77: HR/26-27/01963 | D77: Inv | E77: 2026-09-13 | F77: 2026-10-13 | G77: 94,208.00 | H77: ₹ | K77: PO-2190
C78: HR/26-27/02417 | D78: INV | E78: 29/09/2026 | F78: 29/10/2026 | G78: 36,693.87 | H78: INR | I78: 30D | J78: divya | K78: PO-9401
C79: ** Customer total ** | G79: 40,022.59 | H79: INR
A80: C10037 | B80: Malnad Agro Foods Pvt Ltd | C80: HR/26-27/00034 | D80: INV | E80: 13/04/2026 | F80: 13/05/2026 | G80: 38,425.99 | I80: N30 | J80: Suresh Babu | K80: PO-1632
C81: HR/26-27/00172 | D81: INVOICE | E81: 04/05/2026 | F81: 03/06/2026 | G81: ₹ 40,829.42 | H81: INR | I81: 30D | J81: S Babu | K81: WO-950
C82: HR/26-27/00523 | D82: inv | E82: 21/06/2026 | F82: 21/07/2026 | G82: Rs. 2,950.00 | H82: INR | I82: Net 30 | J82: Suresh Babu | K82: PO/26/115 | L82: PTP next week
C83: hr/26-27/00696 | D83: INV | E83: 10/07/2026 | F83: 09/08/2026 | G83: 140,774.00 | H83: INR | I83: 30 days | J83: S Babu | K83: PO/25/697
C84: HR/26-27/01118 | D84: INV | E84: 03/08/2026 | F84: 02/09/2026 | G84: 13334.00 | H84: INR | I84: NET30 | J84: Suresh B.
C85: RCT/26-27/00352 | D85: PMT | E85: 03/09/2026 | G85: 229,500.00- | H85: INR | I85: Immediate | J85: Suresh Babu | K85: NEFT 3163469018
C86: CN/26-27/0118 | D86: CN | E86: 17/09/2026 | F86: 17/09/2026 | G86: (22,900.00) | H86: INR | J86: Suresh Babu | K86: ret. goods
C87: HR/26-27/02187 | D87: INV | E87: 19-Sep-26 | F87: 19-Oct-26 | G87: 53,872.00 | H87: INR | I87: N30 | J87: Suresh B. | K87: PO-7077 | L87: on hold - site closed
C88: HR/26-27/02191 | D88: INV | E88: 20/09/2026 | F88: 20/10/2026 | G88: 3,47,156.00 | I88: Net30 | K88: WO-188
C89: HR/26-27/02199 | D89: INV | E89: 20 Sep 2026 | F89: 20 Oct 2026 | G89: 21,594.00 | H89: INR | I89: 30 days | J89: Suresh Babu
C90: HR/26-27/02404 | D90: INV | E90: 28/09/2026 | F90: 28/10/2026 | G90: 34,720.00 | H90: INR | I90: 30 Days | J90: Suresh Babu | K90: PO-8114
C91: ** Customer total ** | G91: 4,41,255.41 | H91: INR
A93: C10048 | B93: Brightway Components GmbH | C93: EXP/25-26/0003 | D93: INV | E93: 05/03/2026 | F93: 04/05/2026 | G93: 21,306.14 | H93: EUR | I93: N60 | J93: ANITHA R | K93: PO-5165 | L93: bounced chq - redeposit
C94: EXP/25-26/0328 | D94: INV | E94: 23/03/2026 | F94: 22/05/2026 | G94: 2550.00 | H94: € | I94: Net 60 | J94: A. Rao | K94: PO/25/887
C95: EXP/26-27/0111 | D95: INV | E95: 11/09/2026 | F95: 10/11/2026 | G95: 712.33 | H95: EUR | I95: N60 | J95: Anitha Rao | K95: WO-361
C96: EXP/26-27/0305 | D96: INV | E96: 12/09/2026 | F96: 11/11/2026 | G96: 5,318.67 | H96: EUR | I96: Net 60 | J96: Anitha Rao | K96: none
C97: ** Customer total ** | G97: 29,887.14 | H97: EUR
A99: c10050 | B99: Deccan Pumps & Motors Private Limited | C99: HR/25-26/00340 | D99: INV | E99: 26/08/2025 | F99: 25/10/2025 | G99: Rs. 102,306.00 | H99: INR | I99: 60 Days | J99: D. Nair | K99: PO/26/137
C100: HR/25-26/00688 | D100: INV | E100: 07 Nov 2025 | F100: 06/01/2026 | G100: 174,640.00 | H100: INR | I100: Net 60 | J100: Divya N. | K100: PO-6871
C101: CN/25-26/0080 | D101: Cr Note | E101: 31/12/2025 | F101: 31/12/2025 | G101: (46,479.44) | H101: INR | I101: Immediate | J101: D. Nair
C102: HR/25-26/01869 | D102: INV | E102: 10/01/2026 | F102: 11/03/2026 | G102: 52,015.24 | H102: INR | I102: 60 Days | J102: divya | K102: PO/25/517
C103: HR/26-27/00124 | D103: INV | E103: 30/04/2026 | F103: 29/06/2026 | G103: ₹ 179,043.32 | H103: INR | I103: N60 | J103: Divya N. | K103: 4556588637 | L103: promised end of month
A104: Page 2 of 13
A106: Hosur Road Industrial Supplies Pvt Ltd | G106: AR Open Items
A107: Cust Code | B107: Customer Name | C107: Doc No | D107: Type | E107: Doc Date | F107: Due Date | G107: Amount | H107: Curr | I107: Terms | J107: Sales Rep | K107: PO / Ref | L107: Remarks
A108: C10050 | C108: HR/26-27/00124 | D108: INV | E108: 30/04/2026 | F108: 29/06/2026 | G108: ₹ 179,043.32 | H108: INR | I108: N60 | J108: Divya N. | K108: 4556588637 | L108: promised end of month
C109: HR/26-27/00128 | D109: INV | E109: 30/04/2026 | F109: 29/06/2026 | G109: 784,464.00 | H109: INR | I109: Net 60 | J109: D. Nair | K109: PO-8672
...

Sheet Cleaned_Data
A1: CustCode | B1: CustomerName | C1: Region | D1: Segment | E1: DocNo | F1: DocType | G1: DocDate | H1: DueDate | I1: TermsDays | J1: Currency | K1: Amount | L1: SalesRep | M1: PORef | N1: Remarks | O1: IsDisputed | P1: DaysPastDue | Q1: AgingBucket | R1: DataFlag
A2: C10008 | B2: Sagar Polypack | C2: Andhra Pradesh | D2: Packaging | E2: HR/25-26/01088 | F2: Invoice | G2: 46000 | H2: 46030 | I2: 30 | J2: INR | K2: 96594.74 | L2: Anitha Rao | M2: PO/26/738 | O2: =FALSE() -> FALSE | P2: 265 | Q2: 180+
A3: C10008 | B3: Sagar Polypack | C3: Andhra Pradesh | D3: Packaging | E3: JV/25-26/0031 | F3: Journal | G3: 46080 | H3: 46080 | I3: 0 | J3: INR | K3: -18185.08 | L3: Anitha Rao | O3: =FALSE() -> FALSE | P3: 215 | Q3: 180+
A4: C10008 | B4: Sagar Polypack | C4: Andhra Pradesh | D4: Packaging | E4: HR/25-26/03028 | F4: Invoice | G4: 46084 | H4: 46114 | I4: 30 | J4: INR | K4: 44604 | L4: Anitha Rao | N4: PTP 15/10 | O4: =FALSE() -> FALSE | P4: 181 | Q4: 180+ | R4: terms blank - master default
A5: C10008 | B5: Sagar Polypack | C5: Andhra Pradesh | D5: Packaging | E5: HR/25-26/04023 | F5: Invoice | G5: 46110 | H5: 46140 | I5: 30 | J5: INR | K5: 39270 | L5: Anitha Rao | M5: PO/26/116 | O5: =FALSE() -> FALSE | P5: 155 | Q5: 91-180 | R5: due date missing - derived from terms
A6: C10008 | B6: Sagar Polypack | C6: Andhra Pradesh | D6: Packaging | E6: HR/26-27/00424 | F6: Invoice | G6: 46178 | H6: 46208 | I6: 30 | J6: INR | K6: 104685 | L6: Anitha Rao | M6: PO-5305 | O6: =FALSE() -> FALSE | P6: 87 | Q6: 61-90
A7: C10008 | B7: Sagar Polypack | C7: Andhra Pradesh | D7: Packaging | E7: HR/26-27/00691 | F7: Invoice | G7: 46211 | H7: 46241 | I7: 30 | J7: INR | K7: 17346 | L7: Unassigned | O7: =FALSE() -> FALSE | P7: 54 | Q7: 31-60
A8: C10008 | B8: Sagar Polypack | C8: Andhra Pradesh | D8: Packaging | E8: HR/26-27/00716 | F8: Invoice | G8: 46214 | H8: 46244 | I8: 30 | J8: INR | K8: 224663.47 | L8: Anitha Rao | M8: PO/26/505 | O8: =FALSE() -> FALSE | P8: 51 | Q8: 31-60
A9: C10008 | B9: Sagar Polypack | C9: Andhra Pradesh | D9: Packaging | E9: DN/26-27/0016 | F9: Debit Note | G9: 46236 | H9: 46266 | I9: 30 | J9: INR | K9: 1988.36 | L9: Anitha Rao | M9: PO-5807 | O9: =FALSE() -> FALSE | P9: 29 | Q9: 1-30
A10: C10008 | B10: Sagar Polypack | C10: Andhra Pradesh | D10: Packaging | E10: HR/26-27/01104 | F10: Invoice | G10: 46236 | H10: 46266 | I10: 30 | J10: INR | K10: 80478.64 | L10: Anitha Rao | M10: WO-624 | O10: =FALSE() -> FALSE | P10: 29 | Q10: 1-30 | R10: currency blank - assumed INR
A11: C10008 | B11: Sagar Polypack | C11: Andhra Pradesh | D11: Packaging | E11: HR/26-27/01160 | F11: Invoice | G11: 46240 | H11: 46270 | I11: 30 | J11: INR | K11: 138916.85 | L11: Anitha Rao | M11: PO-6241 | O11: =FALSE() -> FALSE | P11: 25 | Q11: 1-30
A12: C10008 | B12: Sagar Polypack | C12: Andhra Pradesh | D12: Packaging | E12: HR/26-27/01487 | F12: Invoice | G12: 46260 | H12: 46275 | I12: 15 | J12: INR | K12: 50268 | L12: Anitha Rao | M12: 4597152166 | O12: =FALSE() -> FALSE | P12: 20 | Q12: 1-30
A13: C10008 | B13: Sagar Polypack | C13: Andhra Pradesh | D13: Packaging | E13: HR/26-27/01874 | F13: Invoice | G13: 46274 | H13: 46304 | I13: 30 | J13: INR | K13: 84684.97 | L13: Anitha Rao | O13: =FALSE() -> FALSE | P13: -9 | Q13: Not due
A14: C10008 | B14: Sagar Polypack | C14: Andhra Pradesh | D14: Packaging | E14: HR/26-27/02095 | F14: Invoice | G14: 46282 | H14: 46312 | I14: 30 | J14: INR | K14: 368450.74 | L14: Anitha Rao | M14: PO/25/481 | O14: =FALSE() -> FALSE | P14: -17 | Q14: Not due
A15: C10008 | B15: Sagar Polypack | C15: Andhra Pradesh | D15: Packaging | E15: HR/26-27/02244 | F15: Invoice | G15: 46286 | H15: 46316 | I15: 30 | J15: INR | K15: 192340 | L15: Anitha Rao | M15: PO-8122 | O15: =FALSE() -> FALSE | P15: -21 | Q15: Not due
A16: C10008 | B16: Sagar Polypack | C16: Andhra Pradesh | D16: Packaging | E16: HR/26-27/02376 | F16: Invoice | G16: 46291 | H16: 46321 | I16: 30 | J16: INR | K16: 147618 | L16: Anitha Rao | M16: PO/26/467 | O16: =FALSE() -> FALSE | P16: -26 | Q16: Not due
A17: C10011 | B17: Sri Lakshmi Traders | C17: Tamil Nadu | D17: Trading | E17: CN/26-27/0071 | F17: Credit Note | G17: 46242 | H17: 46242 | I17: 0 | J17: INR | K17: -20619.99 | L17: Divya Nair | O17: =FALSE() -> FALSE | P17: 53 | Q17: 31-60
A18: C10011 | B18: Sri Lakshmi Traders | C18: Tamil Nadu | D18: Trading | E18: HR/26-27/01548 | F18: Invoice | G18: 46261 | H18: 46291 | I18: 30 | J18: INR | K18: 140774 | L18: Divya Nair | O18: =FALSE() -> FALSE | P18: 4 | Q18: 1-30
A19: C10017 | B19: Jayanagar Hardware Mart | C19: Bengaluru | D19: Trading | E19: HR/26-27/00720 | F19: Invoice | G19: 46217 | H19: 46232 | I19: 15 | J19: INR | K19: 61360 | L19: Anitha Rao | O19: =FALSE() -> FALSE | P19: 63 | Q19: 61-90
A20: C10017 | B20: Jayanagar Hardware Mart | C20: Bengaluru | D20: Trading | E20: HR/26-27/01368 | F20: Invoice | G20: 46255 | H20: 46270 | I20: 15 | J20: INR | K20: 28084 | L20: Anitha Rao | O20: =FALSE() -> FALSE | P20: 25 | Q20: 1-30
A21: C10017 | B21: Jayanagar Hardware Mart | C21: Bengaluru | D21: Trading | E21: HR/26-27/01665 | F21: Invoice | G21: 46267 | H21: 46282 | I21: 15 | J21: INR | K21: 15340 | L21: Anitha Rao | O21: =FALSE() -> FALSE | P21: 13 | Q21: 1-30
A22: C10021 | B22: Konkan Marine Equipments | C22: Maharashtra | D22: Engineering | E22: HR/25-26/00693 | F22: Invoice | G22: 45974 | H22: 46019 | I22: 45 | J22: INR | K22: 57015 | L22: Suresh Babu | M22: PO-2314 | N22: part payment recd, bal pending | O22: =FALSE() -> FALSE | P22: 276 | Q22: 180+
A23: C10021 | B23: Konkan Marine Equipments | C23: Maharashtra | D23: Engineering | E23: HR/25-26/02229 | F23: Invoice | G23: 46039 | H23: 46084 | I23: 45 | J23: INR | K23: 560146 | L23: Anitha Rao | M23: PO/25/476 | O23: =FALSE() -> FALSE | P23: 211 | Q23: 180+
A24: C10021 | B24: Konkan Marine Equipments | C24: Maharashtra | D24: Engineering | E24: HR/25-26/03868 | F24: Invoice | G24: 46107 | H24: 46152 | I24: 45 | J24: INR | K24: 27258 | L24: Anitha Rao | M24: PO/25/676 | O24: =FALSE() -> FALSE | P24: 143 | Q24: 91-180
A25: C10021 | B25: Konkan Marine Equipments | C25: Maharashtra | D25: Engineering | E25: HR/25-26/04223 | F25: Invoice | G25: 46112 | H25: 46157 | I25: 45 | J25: INR | K25: 25760 | L25: Anitha Rao | O25: =FALSE() -> FALSE | P25: 138 | Q25: 91-180
A26: C10021 | B26: Konkan Marine Equipments | C26: Maharashtra | D26: Engineering | E26: HR/26-27/00413 | F26: Invoice | G26: 46176 | H26: 46221 | I26: 45 | J26: INR | K26: 606900 | L26: Ramesh Kumar | M26: PO-1164 | O26: =FALSE() -> FALSE | P26: 74 | Q26: 61-90
A27: C10021 | B27: Konkan Marine Equipments | C27: Maharashtra | D27: Engineering | E27: DN/26-27/0002 | F27: Debit Note | G27: 46178 | H27: 46223 | I27: 45 | J27: INR | K27: 4480 | L27: Anitha Rao | M27: WO-495 | O27: =FALSE() -> FALSE | P27: 72 | Q27: 61-90
A28: C10021 | B28: Konkan Marine Equipments | C28: Maharashtra | D28: Engineering | E28: HR/26-27/00489 | F28: Invoice | G28: 46191 | H28: 46236 | I28: 45 | J28: INR | K28: 402380 | L28: Anitha Rao | O28: =FALSE() -> FALSE | P28: 59 | Q28: 31-60
A29: C10021 | B29: Konkan Marine Equipments | C29: Maharashtra | D29: Engineering | E29: HR/26-27/00876 | F29: Invoice | G29: 46224 | H29: 46269 | I29: 45 | J29: INR | K29: 46451.21 | L29: Anitha Rao | M29: PO-6449 | O29: =FALSE() -> FALSE | P29: 26 | Q29: 1-30
A30: C10021 | B30: Konkan Marine Equipments | C30: Maharashtra | D30: Engineering | E30: HR/26-27/00973 | F30: Invoice | G30: 46229 | H30: 46274 | I30: 45 | J30: INR | K30: 11303.68 | L30: Unassigned | M30: 4512095782 | O30: =FALSE() -> FALSE | P30: 21 | Q30: 1-30
A31: C10021 | B31: Konkan Marine Equipments | C31: Maharashtra | D31: Engineering | E31: HR/26-27/01162 | F31: Invoice | G31: 46241 | H31: 46286 | I31: 45 | J31: INR | K31: 56286 | L31: Anitha Rao | M31: PO-4393 | O31: =FALSE() -> FALSE | P31: 9 | Q31: 1-30
A32: C10021 | B32: Konkan Marine Equipments | C32: Maharashtra | D32: Engineering | E32: HR/26-27/01344 | F32: Invoice | G32: 46253 | H32: 46298 | I32: 45 | J32: INR | K32: 66394.53 | L32: Anitha Rao | M32: WO-551 | O32: =FALSE() -> FALSE | P32: -3 | Q32: Not due
A33: C10021 | B33: Konkan Marine Equipments | C33: Maharashtra | D33: Engineering | E33: HR/26-27/01363 | F33: Invoice | G33: 46255 | H33: 46315 | I33: 60 | J33: INR | K33: 35754 | L33: Anitha Rao | M33: PO-9573 | O33: =FALSE() -> FALSE | P33: -20 | Q33: Not due
A34: C10021 | B34: Konkan Marine Equipments | C34: Maharashtra | D34: Engineering | E34: CN/26-27/0087 | F34: Credit Note | G34: 46256 | H34: 46256 | I34: 0 | J34: INR | K34: -55658.43 | L34: Unassigned | M34: ret. goods | O34: =FALSE() -> FALSE | P34: 39 | Q34: 31-60
A35: C10021 | B35: Konkan Marine Equipments | C35: Maharashtra | D35: Engineering | E35: HR/26-27/01968 | F35: Invoice | G35: 46279 | H35: 46324 | I35: 45 | J35: INR | K35: 45062.24 | L35: Anitha Rao | M35: PO/25/366 | O35: =FALSE() -> FALSE | P35: -29 | Q35: Not due
A36: C10021 | B36: Konkan Marine Equipments | C36: Maharashtra | D36: Engineering | E36: HR/26-27/01988 | F36: Invoice | G36: 46280 | H36: 46325 | I36: 45 | J36: INR | K36: 73925.76 | L36: Anitha Rao | M36: WO-367 | O36: =FALSE() -> FALSE | P36: -30 | Q36: Not due
A37: C10021 | B37: Konkan Marine Equipments | C37: Maharashtra | D37: Engineering | E37: HR/26-27/02020 | F37: Invoice | G37: 46280 | H37: 46325 | I37: 45 | J37: INR | K37: 81920 | L37: Anitha Rao | M37: PO/26/267 | O37: =FALSE() -> FALSE | P37: -30 | Q37: Not due | R37: due date missing - derived from terms
A38: C10021 | B38: Konkan Marine Equipments | C38: Maharashtra | D38: Engineering | E38: HR/26-27/02104 | F38: Invoice | G38: 46283 | H38: 46328 | I38: 45 | J38: INR | K38: 476838 | L38: Anitha Rao | M38: PO-9754 | O38: =FALSE() -> FALSE | P38: -33 | Q38: Not due
A39: C10021 | B39: Konkan Marine Equipments | C39: Maharashtra | D39: Engineering | E39: HR/26-27/02194 | F39: Invoice | G39: 46285 | H39: 46330 | I39: 45 | J39: INR | K39: 37760 | L39: Anitha Rao | M39: PO-8511 | O39: =FALSE() -> FALSE | P39: -35 | Q39: Not due
A40: C10029 | B40: Peenya Precision Tools | C40: Bengaluru | D40: Engineering | E40: HR/26-27/00299 | F40: Invoice | G40: 46163 | H40: 46208 | I40: 45 | J40: INR | K40: 46964 | L40: Suresh Babu | M40: PO-9393 | N40: PTP 15/10 | O40: =FALSE() -> FALSE | P40: 87 | Q40: 61-90
A41: C10029 | B41: Peenya Precision Tools | C41: Bengaluru | D41: Engineering | E41: HR/26-27/00481 | F41: Invoice | G41: 46190 | H41: 46220 | I41: 30 | J41: INR | K41: 38114 | L41: Unassigned | M41: WO-204 | O41: =FALSE() -> FALSE | P41: 75 | Q41: 61-90
A42: C10029 | B42: Peenya Precision Tools | C42: Bengaluru | D42: Engineering | E42: HR/26-27/00546 | F42: Invoice | G42: 46198 | H42: 46213 | I42: 15 | J42: INR | K42: 33866 | L42: Suresh Babu | M42: PO-9408 | N42: dispute qty | O42: =TRUE() -> TRUE | P42: 82 | Q42: 61-90
A43: C10029 | B43: Peenya Precision Tools | C43: Bengaluru | D43: Engineering | E43: HR/26-27/00855 | F43: Invoice | G43: 46224 | H43: 46254 | I43: 30 | J43: INR | K43: 52392 | L43: Suresh Babu | M43: WO-876 | N43: dispute qty | O43: =TRUE() -> TRUE | P43: 41 | Q43: 31-60
A44: C10029 | B44: Peenya Precision Tools | C44: Bengaluru | D44: Engineering | E44: HR/26-27/01660 | F44: Invoice | G44: 46267 | H44: 46312 | I44: 45 | J44: INR | K44: 48852 | L44: Suresh Babu | M44: WO-141 | O44: =FALSE() -> FALSE | P44: -17 | Q44: Not due
A45: C10029 | B45: Peenya Precision Tools | C45: Bengaluru | D45: Engineering | E45: HR/26-27/01674 | F45: Invoice | G45: 46267 | H45: 46312 | I45: 45 | J45: INR | K45: 148102.33 | L45: Suresh Babu | M45: PO-1581 | O45: =FALSE() -> FALSE | P45: -17 | Q45: Not due
A46: C10029 | B46: Peenya Precision Tools | C46: Bengaluru | D46: Engineering | E46: HR/26-27/02100 | F46: Invoice | G46: 46282 | H46: 46327 | I46: 45 | J46: INR | K46: 49560 | L46: Suresh Babu | M46: PO-3043 | O46: =FALSE() -> FALSE | P46: -32 | Q46: Not due | R46: currency blank - assumed INR
A47: C10029 | B47: Peenya Precision Tools | C47: Bengaluru | D47: Engineering | E47: HR/26-27/02169 | F47: Invoice | G47: 46284 | H47: 46329 | I47: 45 | J47: INR | K47: 125272.26 | L47: Suresh Babu | M47: WO-798 | O47: =FALSE() -> FALSE | P47: -34 | Q47: Not due
A48: C10029 | B48: Peenya Precision Tools | C48: Bengaluru | D48: Engineering | E48: HR/26-27/02355 | F48: Invoice | G48: 46290 | H48: 46335 | I48: 45 | J48: INR | K48: 65735.53 | L48: Suresh Babu | M48: as discussed | O48: =FALSE() -> FALSE | P48: -40 | Q48: Not due
A49: C10029 | B49: Peenya Precision Tools | C49: Bengaluru | D49: Engineering | E49: HR/26-27/02389 | F49: Invoice | G49: 46292 | H49: 46322 | I49: 30 | J49: INR | K49: 179664.78 | L49: Suresh Babu | M49: PO-5221 | O49: =FALSE() -> FALSE | P49: -27 | Q49: Not due
A50: C10031 | B50: Hosakote Industrial Estate Traders | C50: Karnataka | D50: Trading | E50: HR/25-26/02270 | F50: Invoice | G50: 46041 | H50: 46071 | I50: 30 | J50: INR | K50: 87438 | L50: Divya Nair | M50: PO-2191 | O50: =FALSE() -> FALSE | P50: 224 | Q50: 180+
A51: C10031 | B51: Hosakote Industrial Estate Traders | C51: Karnataka | D51: Trading | E51: HR/25-26/02496 | F51: Invoice | G51: 46062 | H51: 46092 | I51: 30 | J51: INR | K51: 6844 | L51: Divya Nair | M51: PO-4685 | O51: =FALSE() -> FALSE | P51: 203 | Q51: 180+
A52: C10031 | B52: Hosakote Industrial Estate Traders | C52: Karnataka | D52: Trading | E52: HR/26-27/00371 | F52: Invoice | G52: 46169 | H52: 46199 | I52: 30 | J52: INR | K52: 89798 | L52: Divya Nair | M52: PO-5478 | O52: =FALSE() -> FALSE | P52: 96 | Q52: 91-180
A53: C10031 | B53: Hosakote Industrial Estate Traders | C53: Karnataka | D53: Trading | E53: RCT/26-27/00024 | F53: On-Account Receipt | G53: 46184 | H53: 46184 | I53: 0 | J53: INR | K53: -452900 | L53: Divya Nair | O53: =FALSE() -> FALSE | P53: 111 | Q53: 91-180 | R53: sign corrected
A54: C10031 | B54: Hosakote Industrial Estate Traders | C54: Karnataka | D54: Trading | E54: HR/26-27/00901 | F54: Invoice | G54: 46226 | H54: 46256 | I54: 30 | J54: INR | K54: 12238.72 | L54: Divya Nair | M54: PO-6587 | O54: =FALSE() -> FALSE | P54: 39 | Q54: 31-60 | R54: due date missing - derived from terms
A55: C10031 | B55: Hosakote Industrial Estate Traders | C55: Karnataka | D55: Trading | E55: CN/26-27/0055 | F55: Credit Note | G55: 46228 | H55: 46228 | I55: 0 | J55: INR | K55: -15900 | L55: Divya Nair | O55: =FALSE() -> FALSE | P55: 67 | Q55: 61-90
A56: C10031 | B56: Hosakote Industrial Estate Traders | C56: Karnataka | D56: Trading | E56: HR/26-27/01897 | F56: Invoice | G56: 46275 | H56: 46305 | I56: 30 | J56: INR | K56: 35282 | L56: Divya Nair | M56: WO-380 | O56: =FALSE() -> FALSE | P56: -10 | Q56: Not due
A57: C10031 | B57: Hosakote Industrial Estate Traders | C57: Karnataka | D57: Trading | E57: HR/26-27/01962 | F57: Invoice | G57: 46278 | H57: 46308 | I57: 30 | J57: INR | K57: 146320 | L57: Suresh Babu | M57: PO-4331 | O57: =FALSE() -> FALSE | P57: -13 | Q57: Not due | R57: due date missing - derived from terms
A58: C10031 | B58: Hosakote Industrial Estate Traders | C58: Karnataka | D58: Trading | E58: HR/26-27/01963 | F58: Invoice | G58: 46278 | H58: 46308 | I58: 30 | J58: INR | K58: 94208 | L58: Unassigned | M58: PO-2190 | O58: =FALSE() -> FALSE | P58: -13 | Q58: Not due | R58: terms blank - master default
A59: C10031 | B59: Hosakote Industrial Estate Traders | C59: Karnataka | D59: Trading | E59: HR/26-27/02417 | F59: Invoice | G59: 46294 | H59: 46324 | I59: 30 | J59: INR | K59: 36693.87 | L59: Divya Nair | M59: PO-9401 | O59: =FALSE() -> FALSE | P59: -29 | Q59: Not due
A60: C10037 | B60: Malnad Agro Foods Pvt Ltd | C60: Karnataka | D60: Agri | E60: HR/26-27/00034 | F60: Invoice | G60: 46125 | H60: 46155 | I60: 30 | J60: INR | K60: 38425.99 | L60: Suresh Babu | M60: PO-1632 | O60: =FALSE() -> FALSE | P60: 140 | Q60: 91-180 | R60: currency blank - assumed INR
A61: C10037 | B61: Malnad Agro Foods Pvt Ltd | C61: Karnataka | D61: Agri | E61: HR/26-27/00172 | F61: Invoice | G61: 46146 | H61: 46176 | I61: 30 | J61: INR | K61: 40829.42 | L61: Suresh Babu | M61: WO-950 | O61: =FALSE() -> FALSE | P61: 119 | Q61: 91-180
A62: C10037 | B62: Malnad Agro Foods Pvt Ltd | C62: Karnataka | D62: Agri | E62: HR/26-27/00523 | F62: Invoice | G62: 46194 | H62: 46224 | I62: 30 | J62: INR | K62: 2950 | L62: Suresh Babu | M62: PO/26/115 | N62: PTP next week | O62: =FALSE() -> FALSE | P62: 71 | Q62: 61-90
A63: C10037 | B63: Malnad Agro Foods Pvt Ltd | C63: Karnataka | D63: Agri | E63: HR/26-27/00696 | F63: Invoice | G63: 46213 | H63: 46243 | I63: 30 | J63: INR | K63: 140774 | L63: Suresh Babu | M63: PO/25/697 | O63: =FALSE() -> FALSE | P63: 52 | Q63: 31-60
A64: C10037 | B64: Malnad Agro Foods Pvt Ltd | C64: Karnataka | D64: Agri | E64: HR/26-27/01118 | F64: Invoice | G64: 46237 | H64: 46267 | I64: 30 | J64: INR | K64: 13334 | L64: Suresh Babu | O64: =FALSE() -> FALSE | P64: 28 | Q64: 1-30
A65: C10037 | B65: Malnad Agro Foods Pvt Ltd | C65: Karnataka | D65: Agri | E65: RCT/26-27/00352 | F65: On-Account Receipt | G65: 46268 | H65: 46268 | I65: 0 | J65: INR | K65: -229500 | L65: Suresh Babu | M65: NEFT 3163469018 | O65: =FALSE() -> FALSE | P65: 27 | Q65: 1-30
A66: C10037 | B66: Malnad Agro Foods Pvt Ltd | C66: Karnataka | D66: Agri | E66: CN/26-27/0118 | F66: Credit Note | G66: 46282 | H66: 46282 | I66: 0 | J66: INR | K66: -22900 | L66: Suresh Babu | M66: ret. goods | O66: =FALSE() -> FALSE | P66: 13 | Q66: 1-30
A67: C10037 | B67: Malnad Agro Foods Pvt Ltd | C67: Karnataka | D67: Agri | E67: HR/26-27/02187 | F67: Invoice | G67: 46284 | H67: 46314 | I67: 30 | J67: INR | K67: 53872 | L67: Suresh Babu | M67: PO-7077 | N67: on hold - site closed | O67: =FALSE() -> FALSE | P67: -19 | Q67: Not due
A68: C10037 | B68: Malnad Agro Foods Pvt Ltd | C68: Karnataka | D68: Agri | E68: HR/26-27/02191 | F68: Invoice | G68: 46285 | H68: 46315 | I68: 30 | J68: INR | K68: 347156 | L68: Unassigned | M68: WO-188 | O68: =FALSE() -> FALSE | P68: -20 | Q68: Not due | R68: currency blank - assumed INR
A69: C10037 | B69: Malnad Agro Foods Pvt Ltd | C69: Karnataka | D69: Agri | E69: HR/26-27/02199 | F69: Invoice | G69: 46285 | H69: 46315 | I69: 30 | J69: INR | K69: 21594 | L69: Suresh Babu | O69: =FALSE() -> FALSE | P69: -20 | Q69: Not due
A70: C10037 | B70: Malnad Agro Foods Pvt Ltd | C70: Karnataka | D70: Agri | E70: HR/26-27/02404 | F70: Invoice | G70: 46293 | H70: 46323 | I70: 30 | J70: INR | K70: 34720 | L70: Suresh Babu | M70: PO-8114 | O70: =FALSE() -> FALSE | P70: -28 | Q70: Not due
A71: C10048 | B71: Brightway Components GmbH | C71: Export | D71: Automotive | E71: EXP/25-26/0003 | F71: Invoice | G71: 46086 | H71: 46146 | I71: 60 | J71: EUR | K71: 21306.14 | L71: Anitha Rao | M71: PO-5165 | N71: bounced chq - redeposit | O71: =FALSE() -> FALSE | P71: 149 | Q71: 91-180
A72: C10048 | B72: Brightway Components GmbH | C72: Export | D72: Automotive | E72: EXP/25-26/0328 | F72: Invoice | G72: 46104 | H72: 46164 | I72: 60 | J72: EUR | K72: 2550 | L72: Anitha Rao | M72: PO/25/887 | O72: =FALSE() -> FALSE | P72: 131 | Q72: 91-180
A73: C10048 | B73: Brightway Components GmbH | C73: Export | D73: Automotive | E73: EXP/26-27/0111 | F73: Invoice | G73: 46276 | H73: 46336 | I73: 60 | J73: EUR | K73: 712.33 | L73: Anitha Rao | M73: WO-361 | O73: =FALSE() -> FALSE | P73: -41 | Q73: Not due
A74: C10048 | B74: Brightway Components GmbH | C74: Export | D74: Automotive | E74: EXP/26-27/0305 | F74: Invoice | G74: 46277 | H74: 46337 | I74: 60 | J74: EUR | K74: 5318.67 | L74: Anitha Rao | O74: =FALSE() -> FALSE | P74: -42 | Q74: Not due
A75: C10050 | B75: Deccan Pumps & Motors Pvt Ltd | C75: Telangana | D75: Engineering | E75: HR/25-26/00340 | F75: Invoice | G75: 45895 | H75: 45955 | I75: 60 | J75: INR | K75: 102306 | L75: Divya Nair | M75: PO/26/137 | O75: =FALSE() -> FALSE | P75: 340 | Q75: 180+
A76: C10050 | B76: Deccan Pumps & Motors Pvt Ltd | C76: Telangana | D76: Engineering | E76: HR/25-26/00688 | F76: Invoice | G76: 45968 | H76: 46028 | I76: 60 | J76: INR | K76: 174640 | L76: Divya Nair | M76: PO-6871 | O76: =FALSE() -> FALSE | P76: 267 | Q76: 180+
A77: C10050 | B77: Deccan Pumps & Motors Pvt Ltd | C77: Telangana | D77: Engineering | E77: CN/25-26/0080 | F77: Credit Note | G77: 46022 | H77: 46022 | I77: 0 | J77: INR | K77: -46479.44 | L77: Divya Nair | O77: =FALSE() -> FALSE | P77: 273 | Q77: 180+
A78: C10050 | B78: Deccan Pumps & Motors Pvt Ltd | C78: Telangana | D78: Engineering | E78: HR/25-26/01869 | F78: Invoice | G78: 46032 | H78: 46092 | I78: 60 | J78: INR | K78: 52015.24 | L78: Divya Nair | M78: PO/25/517 | O78: =FALSE() -> FALSE | P78: 203 | Q78: 180+
A79: C10050 | B79: Deccan Pumps & Motors Pvt Ltd | C79: Telangana | D79: Engineering | E79: HR/26-27/00124 | F79: Invoice | G79: 46142 | H79: 46202 | I79: 60 | J79: INR | K79: 179043.32 | L79: Divya Nair | M79: 4556588637 | N79: promised end of month | O79: =FALSE() -> FALSE | P79: 93 | Q79: 91-180
A80: C10050 | B80: Deccan Pumps & Motors Pvt Ltd | C80: Telangana | D80: Engineering | E80: HR/26-27/00128 | F80: Invoice | G80: 46142 | H80: 46202 | I80: 60 | J80: INR | K80: 784464 | L80: Divya Nair | M80: PO-8672 | O80: =FALSE() -> FALSE | P80: 93 | Q80: 91-180
A81: C10050 | B81: Deccan Pumps & Motors Pvt Ltd | C81: Telangana | D81: Engineering | E81: HR/26-27/00418 | F81: Invoice | G81: 46177 | H81: 46237 | I81: 60 | J81: INR | K81: 8459.57 | L81: Divya Nair | M81: PO/25/643 | O81: =FALSE() -> FALSE | P81: 58 | Q81: 31-60
A82: C10050 | B82: Deccan Pumps & Motors Pvt Ltd | C82: Telangana | D82: Engineering | E82: HR/26-27/00453 | F82: Invoice | G82: 46183 | H82: 46243 | I82: 60 | J82: INR | K82: 174720 | L82: Divya Nair | M82: PO-1021 | O82: =FALSE() -> FALSE | P82: 52 | Q82: 31-60
A83: C10050 | B83: Deccan Pumps & Motors Pvt Ltd | C83: Telangana | D83: Engineering | E83: HR/26-27/01225 | F83: Invoice | G83: 46248 | H83: 46308 | I83: 60 | J83: INR | K83: 89600 | L83: Divya Nair | M83: WO-108 | O83: =FALSE() -> FALSE | P83: -13 | Q83: Not due
A84: C10050 | B84: Deccan Pumps & Motors Pvt Ltd | C84: Telangana | D84: Engineering | E84: DN/26-27/0017 | F84: Debit Note | G84: 46265 | H84: 46325 | I84: 60 | J84: INR | K84: 16690 | L84: Divya Nair | M84: WO-960 | N84: PTP next week | O84: =FALSE() -> FALSE | P84: -30 | Q84: Not due
A85: C10050 | B85: Deccan Pumps & Motors Pvt Ltd | C85: Telangana | D85: Engineering | E85: HR/26-27/02374 | F85: Invoice | G85: 46290 | H85: 46350 | I85: 60 | J85: INR | K85: 114393.66 | L85: Imran Sheikh | M85: PO-2410 | O85: =FALSE() -> FALSE | P85: -55 | Q85: Not due
A86: C10060 | B86: Bhagyalakshmi Enterprises | C86: Karnataka | D86: Trading | E86: HR/25-26/03239 | F86: Invoice | G86: 46092 | H86: 46122 | I86: 30 | J86: INR | K86: 105492 | L86: Suresh Babu | M86: PO-4311 | O86: =FALSE() -> FALSE | P86: 173 | Q86: 91-180
A87: C10060 | B87: Bhagyalakshmi Enterprises | C87: Karnataka | D87: Trading | E87: HR/26-27/00025 | F87: Invoice | G87: 46123 | H87: 46153 | I87: 30 | J87: INR | K87: 108088 | L87: Imran Sheikh | O87: =FALSE() -> FALSE | P87: 142 | Q87: 91-180
A88: C10060 | B88: Bhagyalakshmi Enterprises | C88: Karnataka | D88: Trading | E88: HR/26-27/00243 | F88: Invoice | G88: 46159 | H88: 46189 | I88: 30 | J88: INR | K88: 23180.76 | L88: Imran Sheikh | O88: =FALSE() -> FALSE | P88: 106 | Q88: 91-180
A89: C10060 | B89: Bhagyalakshmi Enterprises | C89: Karnataka | D89: Trading | E89: HR/26-27/00780 | F89: Invoice | G89: 46220 | H89: 46250 | I89: 30 | J89: INR | K89: 50740 | L89: Imran Sheikh | M89: WO-718 | O89: =FALSE() -> FALSE | P89: 45 | Q89: 31-60
A90: C10060 | B90: Bhagyalakshmi Enterprises | C90: Karnataka | D90: Trading | E90: HR/26-27/00832 | F90: Invoice | G90: 46223 | H90: 46268 | I90: 45 | J90: INR | K90: 37237.34 | L90: Imran Sheikh | M90: PO-5316 | O90: =FALSE() -> FALSE | P90: 27 | Q90: 1-30
A91: C10071 | B91: Godavari Fertiliser Dealers | C91: Andhra Pradesh | D91: Agri | E91: HR/25-26/00022 | F91: Invoice | G91: 45758 | H91: 45803 | I91: 45 | J91: INR | K91: 56981.72 | L91: Divya Nair | M91: WO-473 | O91: =FALSE() -> FALSE | P91: 492 | Q91: 180+
A92: C10071 | B92: Godavari Fertiliser Dealers | C92: Andhra Pradesh | D92: Agri | E92: HR/25-26/00455 | F92: Invoice | G92: 45927 | H92: 45972 | I92: 45 | J92: INR | K92: 108796 | L92: Divya Nair | M92: PO-4840 | O92: =FALSE() -> FALSE | P92: 323 | Q92: 180+
A93: C10071 | B93: Godavari Fertiliser Dealers | C93: Andhra Pradesh | D93: Agri | E93: HR/25-26/00952 | F93: Invoice | G93: 45999 | H93: 46044 | I93: 45 | J93: INR | K93: 40333.23 | L93: Divya Nair | M93: PO/26/325 | O93: =FALSE() -> FALSE | P93: 251 | Q93: 180+
A94: C10071 | B94: Godavari Fertiliser Dealers | C94: Andhra Pradesh | D94: Agri | E94: RCT/25-26/00337 | F94: On-Account Receipt | G94: 46093 | H94: 46093 | I94: 0 | J94: INR | K94: -42000 | L94: Divya Nair | M94: NEFT 8255049531 | O94: =FALSE() -> FALSE | P94: 202 | Q94: 180+
A95: C10071 | B95: Godavari Fertiliser Dealers | C95: Andhra Pradesh | D95: Agri | E95: HR/26-27/00064 | F95: Invoice | G95: 46131 | H95: 46176 | I95: 45 | J95: INR | K95: 187040.84 | L95: Unassigned | M95: WO-505 | O95: =FALSE() -> FALSE | P95: 119 | Q95: 91-180
A96: C10071 | B96: Godavari Fertiliser Dealers | C96: Andhra Pradesh | D96: Agri | E96: HR/26-27/00277 | F96: Invoice | G96: 46161 | H96: 46206 | I96: 45 | J96: INR | K96: 34132.94 | L96: Divya Nair | M96: PO/25/400 | N96: dispute qty | O96: =TRUE() -> TRUE | P96: 89 | Q96: 61-90
A97: C10071 | B97: Godavari Fertiliser Dealers | C97: Andhra Pradesh | D97: Agri | E97: HR/26-27/00340 | F97: Invoice | G97: 46168 | H97: 46213 | I97: 45 | J97: INR | K97: 247181.13 | L97: Divya Nair | M97: PO-8521 | N97: Legal notice sent | O97: =FALSE() -> FALSE | P97: 82 | Q97: 61-90
A98: C10071 | B98: Godavari Fertiliser Dealers | C98: Andhra Pradesh | D98: Agri | E98: HR/26-27/01561 | F98: Invoice | G98: 46262 | H98: 46307 | I98: 45 | J98: INR | K98: 169364.23 | L98: Divya Nair | M98: PO-9371 | O98: =FALSE() -> FALSE | P98: -12 | Q98: Not due | R98: due date missing - derived from terms
A99: C10071 | B99: Godavari Fertiliser Dealers | C99: Andhra Pradesh | D99: Agri | E99: HR/26-27/01858 | F99: Invoice | G99: 46274 | H99: 46319 | I99: 45 | J99: INR | K99: 159536 | L99: Divya Nair | M99: PO-3072 | N99: PTP 15/10 | O99: =FALSE() -> FALSE | P99: -24 | Q99: Not due
A100: C10071 | B100: Godavari Fertiliser Dealers | C100: Andhra Pradesh | D100: Agri | E100: HR/26-27/02337 | F100: Invoice | G100: 46289 | H100: 46334 | I100: 45 | J100: INR | K100: 215822 | L100: Divya Nair | M100: PO-8748 | O100: =FALSE() -> FALSE | P100: -39 | Q100: Not due
...

Sheet Before_After
A1: Before and after - real fields from the raw file
A2: Raw values are shown in quotes so stray spaces are visible. Doc No is the clean document number the row ends up under.
A4: Field | B4: What is wrong | C4: Before (raw) | D4: After (clean) | E4: Query step | F4: Doc No
A5: Customer code | B5: lower case | C5: "c10031" | D5: C10031 | E5: CodeFix | F5: HR/25-26/02270
A6: Customer code | B6: extra dash | C6: "C-10156" | D6: C10156 | E6: CodeFix | F6: HR/25-26/02973
A7: Customer code + name | B7: only printed on first line of the block | C7: (blank) / (blank) | D7: C10008 / Sagar Polypack | E7: FillDown | F7: JV/25-26/0031
A8: Customer name | B8: shouted in capitals | C8: "MAHALAKSHMI FASTENERS" | D8: "Mahalakshmi Fasteners" | E8: JoinCust (master) | F8: HR/25-26/02067
A9: Customer name | B9: company suffix written differently | C9: "Deccan Pumps & Motors Private Limited" | D9: "Deccan Pumps & Motors Pvt Ltd" | E9: JoinCust (master) | F9: HR/25-26/00340
A10: Customer name | B10: new customer, not in master yet | C10: "kumaran alloys" | D10: "Kumaran Alloys" + flag | E10: CustomerName (Text.Proper) + DataFlag | F10: HR/25-26/00203
A11: Doc type | B11: long-hand code | C11: "Cr Note" | D11: Credit Note | E11: DocTypeMap | F11: CN/26-27/0087
A12: Doc type | B12: three codes for the same thing | C12: "ADV" | D12: On-Account Receipt | E12: DocTypeMap | F12: RCT/26-27/00625
A13: Doc no | B13: stray spaces / lower case | C13: " HR/26-27/01968" | D13: "HR/26-27/01968" | E13: DocNoStd | F13: HR/26-27/01968
A14: Doc date | B14: Excel serial number saved as text | C14: "46260" | D14: 2026-08-26 | E14: fnParseDate | F14: HR/26-27/01487
A15: Doc date | B15: dd-Mon-yy | C15: "11-Jul-26" | D15: 2026-07-11 | E15: fnParseDate | F15: HR/26-27/00716
... A34: Remarks | B34: free text dispute note | C34: "DISP" | D34: IsDisputed = TRUE | E34: IsDisputed | F34: HR/25-26/02618

Sheet Issues_Log
A1: Issues found in the raw export
A2: Raw file: 670 lines -> 510 document lines -> 497 clean open items. Counts are lines (or cells, for dates) in the raw file, taken from the CSV.
A4: # | B4: What is wrong in the raw export | C4: How the query handles it | D4: Step | E4: Count
A5: 1 | B5: Report furniture: titles, page footers, blank lines, repeated column headers, customer totals and grand totals | C5: Keep only rows that have a document Type, and drop the repeated header row | D5: DocLines | E5: 160
A6: 2 | B6: Customer code and name printed only on the first line of each customer block | C6: Table.FillDown on both columns | D6: Filled | E6: 439
A7: 3 | B7: Customer code typed several ways (c10031, C-10156, "C 10156", trailing space) | C7: Upper-case, remove dashes and spaces | D7: CodeFix | E7: 17
A8: 4 | B8: Customer name spelled differently from the master (capitals, Pvt. Ltd. / Private Limited, & / and) | C8: Take the name from the customer master, joined on the code | D8: JoinCust | E8: 12
A9: 5 | B9: Customer not in the master | C9: Fall back to the raw name in proper case, and flag the row | D9: CustomerName / DataFlag | E9: 17
A10: 6 | B10: Document type written as INV / Inv / INVOICE, CN / Cr Note, RCT / PMT / ADV and so on | C10: Map to five standard types | D10: DocTypeStd | E10: 86
A11: 7 | B11: Document numbers with stray spaces or lower case | C11: Remove spaces, upper-case | D11: DocNoStd | E11: 60
A12: 8 | B12: Dates in six formats, including Excel serial numbers saved as text (cells, doc date + due date) | C12: fnParseDate tries each format explicitly | D12: DocDateP / DueDateP | E12: 260
A13: 9 | B13: Amounts stored as text: brackets, trailing minus, Rs. / rupee sign, lakh grouping (1,24,500.00) | C13: fnParseAmount strips symbols and commas and applies the sign | D13: AmountP | E13: 123
A14: 10 | B14: Credit notes / receipts printed as positive numbers | C14: Force negative for Credit Note and On-Account Receipt | D14: AmountSigned | E14: 12
A15: 11 | B15: Currency written as INR, Rs, the rupee sign, inr, US$, the euro sign... | C15: Map to ISO codes | D15: Currency | E15: 87
A16: 12 | B16: Currency blank | C16: Assume INR (functional currency) and flag | D16: Currency / DataFlag | E16: 22
... A24: 20 | B24: Lines repeated at the top of the next page, and a few double postings | C24: Distinct on customer + doc no + type + amount (after standardising) | D24: Deduped | E24: 13

Sheet Aging_Summary
A1: Receivables ageing
A3: As on date | B3: 46295 | C3: Input: report date from the raw file header. Ageing buckets in Cleaned_Data were built against this date.
A5: Bucket | B5: INR | C5: USD | D5: EUR | E5: Items
A6: Not due | B6: =SUMIFS(Cleaned_Data!$K$2:$K$498,Cleaned_Data!$Q$2:$Q$498,$A6,Cleaned_Data!$J$2:$J$498,B$5) -> 17475656 | C6: =SUMIFS(Cleaned_Data!$K$2:$K$498,Cleaned_Data!$Q$2:$Q$498,$A6,Cleaned_Data!$J$2:$J$498,C$5) -> 38448.34 | D6: =SUMIFS(Cleaned_Data!$K$2:$K$498,Cleaned_Data!$Q$2:$Q$498,$A6,Cleaned_Data!$J$2:$J$498,D$5) -> 6031 | E6: =COUNTIFS(Cleaned_Data!$Q$2:$Q$498,$A6) -> 153
A7: 1-30 | B7: =SUMIFS(Cleaned_Data!$K$2:$K$498,Cleaned_Data!$Q$2:$Q$498,$A7,Cleaned_Data!$J$2:$J$498,B$5) -> 6971835.1 | C7: =SUMIFS(Cleaned_Data!$K$2:$K$498,Cleaned_Data!$Q$2:$Q$498,$A7,Cleaned_Data!$J$2:$J$498,C$5) -> 25706.53 | D7: =SUMIFS(Cleaned_Data!$K$2:$K$498,Cleaned_Data!$Q$2:$Q$498,$A7,Cleaned_Data!$J$2:$J$498,D$5) -> 0 | E7: =COUNTIFS(Cleaned_Data!$Q$2:$Q$498,$A7) -> 97
A8: 31-60 | B8: =SUMIFS(Cleaned_Data!$K$2:$K$498,Cleaned_Data!$Q$2:$Q$498,$A8,Cleaned_Data!$J$2:$J$498,B$5) -> 4532542.1 | C8: =SUMIFS(Cleaned_Data!$K$2:$K$498,Cleaned_Data!$Q$2:$Q$498,$A8,Cleaned_Data!$J$2:$J$498,C$5) -> 0 | D8: =SUMIFS(Cleaned_Data!$K$2:$K$498,Cleaned_Data!$Q$2:$Q$498,$A8,Cleaned_Data!$J$2:$J$498,D$5) -> 0 | E8: =COUNTIFS(Cleaned_Data!$Q$2:$Q$498,$A8) -> 60
A9: 61-90 | B9: =SUMIFS(Cleaned_Data!$K$2:$K$498,Cleaned_Data!$Q$2:$Q$498,$A9,Cleaned_Data!$J$2:$J$498,B$5) -> 3693329 | C9: =SUMIFS(Cleaned_Data!$K$2:$K$498,Cleaned_Data!$Q$2:$Q$498,$A9,Cleaned_Data!$J$2:$J$498,C$5) -> 1442.48 | D9: =SUMIFS(Cleaned_Data!$K$2:$K$498,Cleaned_Data!$Q$2:$Q$498,$A9,Cleaned_Data!$J$2:$J$498,D$5) -> 0 | E9: =COUNTIFS(Cleaned_Data!$Q$2:$Q$498,$A9) -> 37
A10: 91-180 | B10: =SUMIFS(Cleaned_Data!$K$2:$K$498,Cleaned_Data!$Q$2:$Q$498,$A10,Cleaned_Data!$J$2:$J$498,B$5) -> 7143316.7 | C10: =SUMIFS(Cleaned_Data!$K$2:$K$498,Cleaned_Data!$Q$2:$Q$498,$A10,Cleaned_Data!$J$2:$J$498,C$5) -> 14300.94 | D10: =SUMIFS(Cleaned_Data!$K$2:$K$498,Cleaned_Data!$Q$2:$Q$498,$A10,Cleaned_Data!$J$2:$J$498,D$5) -> 23856.14 | E10: =COUNTIFS(Cleaned_Data!$Q$2:$Q$498,$A10) -> 89
A11: 180+ | B11: =SUMIFS(Cleaned_Data!$K$2:$K$498,Cleaned_Data!$Q$2:$Q$498,$A11,Cleaned_Data!$J$2:$J$498,B$5) -> 5245953.7 | C11: =SUMIFS(Cleaned_Data!$K$2:$K$498,Cleaned_Data!$Q$2:$Q$498,$A11,Cleaned_Data!$J$2:$J$498,C$5) -> -2335.7 | D11: =SUMIFS(Cleaned_Data!$K$2:$K$498,Cleaned_Data!$Q$2:$Q$498,$A11,Cleaned_Data!$J$2:$J$498,D$5) -> 0 | E11: =COUNTIFS(Cleaned_Data!$Q$2:$Q$498,$A11) -> 61
A12: Total | B12: =SUM(B6:B11) -> 45062632 | C12: =SUM(C6:C11) -> 77562.59 | D12: =SUM(D6:D11) -> 29887.14 | E12: =SUM(E6:E11) -> 497
A13: Report grand total (raw file footer) | B13: 45062632 | C13: 77562.59 | D13: 29887.14 | F13: Hard-coded from the "*** GRAND TOTAL ***" lines at the bottom of Raw_Data.
A14: Difference (should be 0) | B14: =ROUND(B12-B13,2) -> 0 | C14: =ROUND(C12-C13,2) -> 0 | D14: =ROUND(D12-D13,2) -> 0
A17: INR ageing by customer
A18: CustCode | B18: Customer | C18: Not due | D18: 1-30 | E18: 31-60 | F18: 61-90 | G18: 91-180 | H18: 180+ | I18: Total
A19: C10008 | B19: Sagar Polypack | C19: =SUMIFS(Cleaned_Data!$K$2:$K$498,Cleaned_Data!$A$2:$A$498,$A19,Cleaned_Data!$J$2:$J$498,"INR",Cleaned_Data!$Q$2:$Q$498,C$18) -> 793093.71 | D19: =SUMIFS(Cleaned_Data!$K$2:$K$498,Cleaned_Data!$A$2:$A$498,$A19,Cleaned_Data!$J$2:$J$498,"INR",Cleaned_Data!$Q$2:$Q$498,D$18) -> 271651.85 | E19: =SUMIFS(Cleaned_Data!$K$2:$K$498,Cleaned_Data!$A$2:$A$498,$A19,Cleaned_Data!$J$2:$J$498,"INR",Cleaned_Data!$Q$2:$Q$498,E$18) -> 242009.47 | F19: =SUMIFS(Cleaned_Data!$K$2:$K$498,Cleaned_Data!$A$2:$A$498,$A19,Cleaned_Data!$J$2:$J$498,"INR",Cleaned_Data!$Q$2:$Q$498,F$18) -> 104685 | G19: =SUMIFS(Cleaned_Data!$K$2:$K$498,Cleaned_Data!$A$2:$A$498,$A19,Cleaned_Data!$J$2:$J$498,"INR",Cleaned_Data!$Q$2:$Q$498,G$18) -> 39270 | H19: =SUMIFS(Cleaned_Data!$K$2:$K$498,Cleaned_Data!$A$2:$A$498,$A19,Cleaned_Data!$J$2:$J$498,"INR",Cleaned_Data!$Q$2:$Q$498,H$18) -> 123013.66 | I19: =SUM(C19:H19) -> 1573723.7
A20: C10011 | B20: Sri Lakshmi Traders | C20: =SUMIFS(Cleaned_Data!$K$2:$K$498,Cleaned_Data!$A$2:$A$498,$A20,Cleaned_Data!$J$2:$J$498,"INR",Cleaned_Data!$Q$2:$Q$498,C$18) -> 0 | D20: =SUMIFS(Cleaned_Data!$K$2:$K$498,Cleaned_Data!$A$2:$A$498,$A20,Cleaned_Data!$J$2:$J$498,"INR",Cleaned_Data!$Q$2:$Q$498,D$18) -> 140774 | E20: =SUMIFS(Cleaned_Data!$K$2:$K$498,Cleaned_Data!$A$2:$A$498,$A20,Cleaned_Data!$J$2:$J$498,"INR",Cleaned_Data!$Q$2:$Q$498,E$18) -> -20619.99 | F20: =SUMIFS(Cleaned_Data!$K$2:$K$498,Cleaned_Data!$A$2:$A$498,$A20,Cleaned_Data!$J$2:$J$498,"INR",Cleaned_Data!$Q$2:$Q$498,F$18) -> 0 | G20: =SUMIFS(Cleaned_Data!$K$2:$K$498,Cleaned_Data!$A$2:$A$498,$A20,Cleaned_Data!$J$2:$J$498,"INR",Cleaned_Data!$Q$2:$Q$498,G$18) -> 0 | H20: =SUMIFS(Cleaned_Data!$K$2:$K$498,Cleaned_Data!$A$2:$A$498,$A20,Cleaned_Data!$J$2:$J$498,"INR",Cleaned_Data!$Q$2:$Q$498,H$18) -> 0 | I20: =SUM(C20:H20) -> 120154.01
A21: C10017 | B21: Jayanagar Hardware Mart | C21: =SUMIFS(Cleaned_Data!$K$2:$K$498,Cleaned_Data!$A$2:$A$498,$A21,Cleaned_Data!$J$2:$J$498,"INR",Cleaned_Data!$Q$2:$Q$498,C$18) -> 0 | D21: =SUMIFS(Cleaned_Data!$K$2:$K$498,Cleaned_Data!$A$2:$A$498,$A21,Cleaned_Data!$J$2:$J$498,"INR",Cleaned_Data!$Q$2:$Q$498,D$18) -> 43424 | E21: =SUMIFS(Cleaned_Data!$K$2:$K$498,Cleaned_Data!$A$2:$A$498,$A21,Cleaned_Data!$J$2:$J$498,"INR",Cleaned_Data!$Q$2:$Q$498,E$18) -> 0 | F21: =SUMIFS(Cleaned_Data!$K$2:$K$498,Cleaned_Data!$A$2:$A$498,$A21,Cleaned_Data!$J$2:$J$498,"INR",Cleaned_Data!$Q$2:$Q$498,F$18) -> 61360 | G21: =SUMIFS(Cleaned_Data!$K$2:$K$498,Cleaned_Data!$A$2:$A$498,$A21,Cleaned_Data!$J$2:$J$498,"INR",Cleaned_Data!$Q$2:$Q$498,G$18) -> 0 | H21: =SUMIFS(Cleaned_Data!$K$2:$K$498,Cleaned_Data!$A$2:$A$498,$A21,Cleaned_Data!$J$2:$J$498,"INR",Cleaned_Data!$Q$2:$Q$498,H$18) -> 0 | I21: =SUM(C21:H21) -> 104784
A22: C10021 | B22: Konkan Marine Equipments | C22: =SUMIFS(Cleaned_Data!$K$2:$K$498,Cleaned_Data!$A$2:$A$498,$A22,Cleaned_Data!$J$2:$J$498,"INR",Cleaned_Data!$Q$2:$Q$498,C$18) -> 817654.53 | D22: =SUMIFS(Cleaned_Data!$K$2:$K$498,Cleaned_Data!$A$2:$A$498,$A22,Cleaned_Data!$J$2:$J$498,"INR",Cleaned_Data!$Q$2:$Q$498,D$18) -> 114040.89 | E22: =SUMIFS(Cleaned_Data!$K$2:$K$498,Cleaned_Data!$A$2:$A$498,$A22,Cleaned_Data!$J$2:$J$498,"INR",Cleaned_Data!$Q$2:$Q$498,E$18) -> 346721.57 | F22: =SUMIFS(Cleaned_Data!$K$2:$K$498,Cleaned_Data!$A$2:$A$498,$A22,Cleaned_Data!$J$2:$J$498,"INR",Cleaned_Data!$Q$2:$Q$498,F$18) -> 611380 | G22: =SUMIFS(Cleaned_Data!$K$2:$K$498,Cleaned_Data!$A$2:$A$498,$A22,Cleaned_Data!$J$2:$J$498,"INR",Cleaned_Data!$Q$2:$Q$498,G$18) -> 53018 | H22: =SUMIFS(Cleaned_Data!$K$2:$K$498,Cleaned_Data!$A$2:$A$498,$A22,Cleaned_Data!$J$2:$J$498,"INR",Cleaned_Data!$Q$2:$Q$498,H$18) -> 617161 | I22: =SUM(C22:H22) -> 2559976
A23: C10029 | B23: Peenya Precision Tools | C23: =SUMIFS(Cleaned_Data!$K$2:$K$498,Cleaned_Data!$A$2:$A$498,$A23,Cleaned_Data!$J$2:$J$498,"INR",Cleaned_Data!$Q$2:$Q$498,C$18) -> 617186.9 | D23: =SUMIFS(Cleaned_Data!$K$2:$K$498,Cleaned_Data!$A$2:$A$498,$A23,Cleaned_Data!$J$2:$J$498,"INR",Cleaned_Data!$Q$2:$Q$498,D$18) -> 0 | E23: =SUMIFS(Cleaned_Data!$K$2:$K$498,Cleaned_Data!$A$2:$A$498,$A23,Cleaned_Data!$J$2:$J$498,"INR",Cleaned_Data!$Q$2:$Q$498,E$18) -> 52392 | F23: =SUMIFS(Cleaned_Data!$K$2:$K$498,Cleaned_Data!$A$2:$A$498,$A23,Cleaned_Data!$J$2:$J$498,"INR",Cleaned_Data!$Q$2:$Q$498,F$18) -> 118944 | G23: =SUMIFS(Cleaned_Data!$K$2:$K$498,Cleaned_Data!$A$2:$A$498,$A23,Cleaned_Data!$J$2:$J$498,"INR",Cleaned_Data!$Q$2:$Q$498,G$18) -> 0 | H23: =SUMIFS(Cleaned_Data!$K$2:$K$498,Cleaned_Data!$A$2:$A$498,$A23,Cleaned_Data!$J$2:$J$498,"INR",Cleaned_Data!$Q$2:$Q$498,H$18) -> 0 | I23: =SUM(C23:H23) -> 788522.9
A24: C10031 | B24: Hosakote Industrial Estate Traders | C24: =SUMIFS(Cleaned_Data!$K$2:$K$498,Cleaned_Data!$A$2:$A$498,$A24,Cleaned_Data!$J$2:$J$498,"INR",Cleaned_Data!$Q$2:$Q$498,C$18) -> 312503.87 | D24: =SUMIFS(Cleaned_Data!$K$2:$K$498,Cleaned_Data!$A$2:$A$498,$A24,Cleaned_Data!$J$2:$J$498,"INR",Cleaned_Data!$Q$2:$Q$498,D$18) -> 0 | E24: =SUMIFS(Cleaned_Data!$K$2:$K$498,Cleaned_Data!$A$2:$A$498,$A24,Cleaned_Data!$J$2:$J$498,"INR",Cleaned_Data!$Q$2:$Q$498,E$18) -> 12238.72 | F24: =SUMIFS(Cleaned_Data!$K$2:$K$498,Cleaned_Data!$A$2:$A$498,$A24,Cleaned_Data!$J$2:$J$498,"INR",Cleaned_Data!$Q$2:$Q$498,F$18) -> -15900 | G24: =SUMIFS(Cleaned_Data!$K$2:$K$498,Cleaned_Data!$A$2:$A$498,$A24,Cleaned_Data!$J$2:$J$498,"INR",Cleaned_Data!$Q$2:$Q$498,G$18) -> -363102 | H24: =SUMIFS(Cleaned_Data!$K$2:$K$498,Cleaned_Data!$A$2:$A$498,$A24,Cleaned_Data!$J$2:$J$498,"INR",Cleaned_Data!$Q$2:$Q$498,H$18) -> 94282 | I24: =SUM(C24:H24) -> 40022.59
A25: C10037 | B25: Malnad Agro Foods Pvt Ltd | C25: =SUMIFS(Cleaned_Data!$K$2:$K$498,Cleaned_Data!$A$2:$A$498,$A25,Cleaned_Data!$J$2:$J$498,"INR",Cleaned_Data!$Q$2:$Q$498,C$18) -> 457342 | D25: =SUMIFS(Cleaned_Data!$K$2:$K$498,Cleaned_Data!$A$2:$A$498,$A25,Cleaned_Data!$J$2:$J$498,"INR",Cleaned_Data!$Q$2:$Q$498,D$18) -> -239066 | E25: =SUMIFS(Cleaned_Data!$K$2:$K$498,Cleaned_Data!$A$2:$A$498,$A25,Cleaned_Data!$J$2:$J$498,"INR",Cleaned_Data!$Q$2:$Q$498,E$18) -> 140774 | F25: =SUMIFS(Cleaned_Data!$K$2:$K$498,Cleaned_Data!$A$2:$A$498,$A25,Cleaned_Data!$J$2:$J$498,"INR",Cleaned_Data!$Q$2:$Q$498,F$18) -> 2950 | G25: =SUMIFS(Cleaned_Data!$K$2:$K$498,Cleaned_Data!$A$2:$A$498,$A25,Cleaned_Data!$J$2:$J$498,"INR",Cleaned_Data!$Q$2:$Q$498,G$18) -> 79255.41 | H25: =SUMIFS(Cleaned_Data!$K$2:$K$498,Cleaned_Data!$A$2:$A$498,$A25,Cleaned_Data!$J$2:$J$498,"INR",Cleaned_Data!$Q$2:$Q$498,H$18) -> 0 | I25: =SUM(C25:H25) -> 441255.41
A26: C10050 | B26: Deccan Pumps & Motors Pvt Ltd | C26: =SUMIFS(Cleaned_Data!$K$2:$K$498,Cleaned_Data!$A$2:$A$498,$A26,Cleaned_Data!$J$2:$J$498,"INR",Cleaned_Data!$Q$2:$Q$498,C$18) -> 220683.66 | D26: =SUMIFS(Cleaned_Data!$K$2:$K$498,Cleaned_Data!$A$2:$A$498,$A26,Cleaned_Data!$J$2:$J$498,"INR",Cleaned_Data!$Q$2:$Q$498,D$18) -> 0 | E26: =SUMIFS(Cleaned_Data!$K$2:$K$498,Cleaned_Data!$A$2:$A$498,$A26,Cleaned_Data!$J$2:$J$498,"INR",Cleaned_Data!$Q$2:$Q$498,E$18) -> 183179.57 | F26: =SUMIFS(Cleaned_Data!$K$2:$K$498,Cleaned_Data!$A$2:$A$498,$A26,Cleaned_Data!$J$2:$J$498,"INR",Cleaned_Data!$Q$2:$Q$498,F$18) -> 0 | G26: =SUMIFS(Cleaned_Data!$K$2:$K$498,Cleaned_Data!$A$2:$A$498,$A26,Cleaned_Data!$J$2:$J$498,"INR",Cleaned_Data!$Q$2:$Q$498,G$18) -> 963507.32 | H26: =SUMIFS(Cleaned_Data!$K$2:$K$498,Cleaned_Data!$A$2:$A$498,$A26,Cleaned_Data!$J$2:$J$498,"INR",Cleaned_Data!$Q$2:$Q$498,H$18) -> 282481.8 | I26: =SUM(C26:H26) -> 1649852.4
A27: C10060 | B27: Bhagyalakshmi Enterprises | C27: =SUMIFS(Cleaned_Data!$K$2:$K$498,Cleaned_Data!$A$2:$A$498,$A27,Cleaned_Data!$J$2:$J$498,"INR",Cleaned_Data!$Q$2:$Q$498,C$18) -> 0 | D27: =SUMIFS(Cleaned_Data!$K$2:$K$498,Cleaned_Data!$A$2:$A$498,$A27,Cleaned_Data!$J$2:$J$498,"INR",Cleaned_Data!$Q$2:$Q$498,D$18) -> 37237.34 | E27: =SUMIFS(Cleaned_Data!$K$2:$K$498,Cleaned_Data!$A$2:$A$498,$A27,Cleaned_Data!$J$2:$J$498,"INR",Cleaned_Data!$Q$2:$Q$498,E$18) -> 50740 | F27: =SUMIFS(Cleaned_Data!$K$2:$K$498,Cleaned_Data!$A$2:$A$498,$A27,Cleaned_Data!$J$2:$J$498,"INR",Cleaned_Data!$Q$2:$Q$498,F$18) -> 0 | G27: =SUMIFS(Cleaned_Data!$K$2:$K$498,Cleaned_Data!$A$2:$A$498,$A27,Cleaned_Data!$J$2:$J$498,"INR",Cleaned_Data!$Q$2:$Q$498,G$18) -> 236760.76 | H27: =SUMIFS(Cleaned_Data!$K$2:$K$498,Cleaned_Data!$A$2:$A$498,$A27,Cleaned_Data!$J$2:$J$498,"INR",Cleaned_Data!$Q$2:$Q$498,H$18) -> 0 | I27: =SUM(C27:H27) -> 324738.1
A28: C10071 | B28: Godavari Fertiliser Dealers | C28: =SUMIFS(Cleaned_Data!$K$2:$K$498,Cleaned_Data!$A$2:$A$498,$A28,Cleaned_Data!$J$2:$J$498,"INR",Cleaned_Data!$Q$2:$Q$498,C$18) -> 544722.23 | D28: =SUMIFS(Cleaned_Data!$K$2:$K$498,Cleaned_Data!$A$2:$A$498,$A28,Cleaned_Data!$J$2:$J$498,"INR",Cleaned_Data!$Q$2:$Q$498,D$18) -> 0 | E28: =SUMIFS(Cleaned_Data!$K$2:$K$498,Cleaned_Data!$A$2:$A$498,$A28,Cleaned_Data!$J$2:$J$498,"INR",Cleaned_Data!$Q$2:$Q$498,E$18) -> 0 | F28: =SUMIFS(Cleaned_Data!$K$2:$K$498,Cleaned_Data!$A$2:$A$498,$A28,Cleaned_Data!$J$2:$J$498,"INR",Cleaned_Data!$Q$2:$Q$498,F$18) -> 281314.07 | G28: =SUMIFS(Cleaned_Data!$K$2:$K$498,Cleaned_Data!$A$2:$A$498,$A28,Cleaned_Data!$J$2:$J$498,"INR",Cleaned_Data!$Q$2:$Q$498,G$18) -> 187040.84 | H28: =SUMIFS(Cleaned_Data!$K$2:$K$498,Cleaned_Data!$A$2:$A$498,$A28,Cleaned_Data!$J$2:$J$498,"INR",Cleaned_Data!$Q$2:$Q$498,H$18) -> 164110.95 | I28: =SUM(C28:H28) -> 1177188.1
A29: C10074 | B29: Tejas Precision Castings | C29: =SUMIFS(Cleaned_Data!$K$2:$K$498,Cleaned_Data!$A$2:$A$498,$A29,Cleaned_Data!$J$2:$J$498,"INR",Cleaned_Data!$Q$2:$Q$498,C$18) -> 617427.11 | D29: =SUMIFS(Cleaned_Data!$K$2:$K$498,Cleaned_Data!$A$2:$A$498,$A29,Cleaned_Data!$J$2:$J$498,"INR",Cleaned_Data!$Q$2:$Q$498,D$18) -> 0 | E29: =SUMIFS(Cleaned_Data!$K$2:$K$498,Cleaned_Data!$A$2:$A$498,$A29,Cleaned_Data!$J$2:$J$498,"INR",Cleaned_Data!$Q$2:$Q$498,E$18) -> 0 | F29: =SUMIFS(Cleaned_Data!$K$2:$K$498,Cleaned_Data!$A$2:$A$498,$A29,Cleaned_Data!$J$2:$J$498,"INR",Cleaned_Data!$Q$2:$Q$498,F$18) -> 0 | G29: =SUMIFS(Cleaned_Data!$K$2:$K$498,Cleaned_Data!$A$2:$A$498,$A29,Cleaned_Data!$J$2:$J$498,"INR",Cleaned_Data!$Q$2:$Q$498,G$18) -> -79000 | H29: =SUMIFS(Cleaned_Data!$K$2:$K$498,Cleaned_Data!$A$2:$A$498,$A29,Cleaned_Data!$J$2:$J$498,"INR",Cleaned_Data!$Q$2:$Q$498,H$18) -> 130527.14 | I29: =SUM(C29:H29) -> 668954.25
A30: C10081 | B30: Maruthi Tools & Dies | C30: =SUMIFS(Cleaned_Data!$K$2:$K$498,Cleaned_Data!$A$2:$A$498,$A30,Cleaned_Data!$J$2:$J$498,"INR",Cleaned_Data!$Q$2:$Q$498,C$18) -> 0 | D30: =SUMIFS(Cleaned_Data!$K$2:$K$498,Cleaned_Data!$A$2:$A$498,$A30,Cleaned_Data!$J$2:$J$498,"INR",Cleaned_Data!$Q$2:$Q$498,D$18) -> 56050 | E30: =SUMIFS(Cleaned_Data!$K$2:$K$498,Cleaned_Data!$A$2:$A$498,$A30,Cleaned_Data!$J$2:$J$498,"INR",Cleaned_Data!$Q$2:$Q$498,E$18) -> 0 | F30: =SUMIFS(Cleaned_Data!$K$2:$K$498,Cleaned_Data!$A$2:$A$498,$A30,Cleaned_Data!$J$2:$J$498,"INR",Cleaned_Data!$Q$2:$Q$498,F$18) -> 0 | G30: =SUMIFS(Cleaned_Data!$K$2:$K$498,Cleaned_Data!$A$2:$A$498,$A30,Cleaned_Data!$J$2:$J$498,"INR",Cleaned_Data!$Q$2:$Q$498,G$18) -> 94147.19 | H30: =SUMIFS(Cleaned_Data!$K$2:$K$498,Cleaned_Data!$A$2:$A$498,$A30,Cleaned_Data!$J$2:$J$498,"INR",Cleaned_Data!$Q$2:$Q$498,H$18) -> 0 | I30: =SUM(C30:H30) -> 150197.19
... A73: C10371 | B73: Vijayanagar Building Supplies | C73: =SUMIFS(Cleaned_Data!$K$2:$K$498,Cleaned_Data!$A$2:$A$498,$A73,Cleaned_Data!$J$2:$J$498,"INR",Cleaned_Data!$Q$2:$Q$498,C$18) -> 84223 | D73: =SUMIFS(Cleaned_Data!$K$2:$K$498,Cleaned_Data!$A$2:$A$498,$A73,Cleaned_Data!$J$2:$J$498,"INR",Cleaned_Data!$Q$2:$Q$498,D$18) -> 16859.8 | E73: =SUMIFS(Cleaned_Data!$K$2:$K$498,Cleaned_Data!$A$2:$A$498,$A73,Cleaned_Data!$J$2:$J$498,"INR",Cleaned_Data!$Q$2:$Q$498,E$18) -> 0 | F73: =SUMIFS(Cleaned_Data!$K$2:$K$498,Cleaned_Data!$A$2:$A$498,$A73,Cleaned_Data!$J$2:$J$498,"INR",Cleaned_Data!$Q$2:$Q$498,F$18) -> 0 | G73: =SUMIFS(Cleaned_Data!$K$2:$K$498,Cleaned_Data!$A$2:$A$498,$A73,Cleaned_Data!$J$2:$J$498,"INR",Cleaned_Data!$Q$2:$Q$498,G$18) -> 0 | H73: =SUMIFS(Cleaned_Data!$K$2:$K$498,Cleaned_Data!$A$2:$A$498,$A73,Cleaned_Data!$J$2:$J$498,"INR",Cleaned_Data!$Q$2:$Q$498,H$18) -> 0 | I73: =SUM(C73:H73) -> 101082.8
A74: Total | C74: =SUM(C19:C73) -> 17475656 | D74: =SUM(D19:D73) -> 6971835.1 | E74: =SUM(E19:E73) -> 4532542.1 | F74: =SUM(F19:F73) -> 3693329 | G74: =SUM(G19:G73) -> 7143316.7 | H74: =SUM(H19:H73) -> 5245953.7 | I74: =SUM(I19:I73) -> 45062632

Sheet Cust_Master
A1: CustCode | B1: CustomerName | C1: Region | D1: Segment | E1: DefaultTermsDays
A2: C10008 | B2: Sagar Polypack | C2: Andhra Pradesh | D2: Packaging | E2: 30
A3: C10011 | B3: Sri Lakshmi Traders | C3: Tamil Nadu | D3: Trading | E3: 30
A4: C10017 | B4: Jayanagar Hardware Mart | C4: Bengaluru | D4: Trading | E4: 15
A5: C10021 | B5: Konkan Marine Equipments | C5: Maharashtra | D5: Engineering | E5: 45
A6: C10029 | B6: Peenya Precision Tools | C6: Bengaluru | D6: Engineering | E6: 45
A7: C10031 | B7: Hosakote Industrial Estate Traders | C7: Karnataka | D7: Trading | E7: 30
A8: C10037 | B8: Malnad Agro Foods Pvt Ltd | C8: Karnataka | D8: Agri | E8: 30
A9: C10048 | B9: Brightway Components GmbH | C9: Export | D9: Automotive | E9: 60
A10: C10050 | B10: Deccan Pumps & Motors Pvt Ltd | C10: Telangana | D10: Engineering | E10: 60
A11: C10060 | B11: Bhagyalakshmi Enterprises | C11: Karnataka | D11: Trading | E11: 30
A12: C10071 | B12: Godavari Fertiliser Dealers | C12: Andhra Pradesh | D12: Agri | E12: 45
A13: C10074 | B13: Tejas Precision Castings | C13: Bengaluru | D13: Automotive | E13: 45
... A58: C10371 | B58: Vijayanagar Building Supplies | C58: Karnataka | D58: Construction | E58: 30

Sheet Rep_Alias
A1: Alias | B1: SalesRep | D1: Alias = the rep name as typed, reduced to lower-case letters (Ramesh K. -> rameshk).
A2: anithar | B2: Anitha Rao
A3: anitharao | B3: Anitha Rao
A4: arao | B4: Anitha Rao
A5: divya | B5: Divya Nair
A6: divyan | B6: Divya Nair
A7: divyanair | B7: Divya Nair
A8: dnair | B8: Divya Nair
A9: imran | B9: Imran Sheikh
A10: imrans | B10: Imran Sheikh
A11: imransheikh | B11: Imran Sheikh
A12: isheikh | B12: Imran Sheikh
A13: phegde | B13: Prakash Hegde
... A24: sureshbabu | B24: Suresh Babu

Sheet M_Code
A1: // AR_Open_Items_Clean
A2: // Raw ERP open-items print (CSV) -> one tidy row per open document.
A3: // Needs: pRepoPath, pAsOfDate, fnCleanText, fnParseDate, fnParseAmount, fnTermsDays, dimCustomer, dimRepAlias
A4: let
A5: // ---- lookups kept at the top so they are easy to extend --------------------------------
A6: DocTypeMap = [
A7: INV = "Invoice", INVOICE = "Invoice",
A8: CN = "Credit Note", #"CR NOTE" = "Credit Note", #"CREDIT NOTE" = "Credit Note",
A9: DN = "Debit Note", #"DR NOTE" = "Debit Note",
A10: PMT = "On-Account Receipt", RCT = "On-Account Receipt", ADV = "On-Account Receipt",
A11: JV = "Journal"
A12: ],
... A207: Sorted
